{"expireTime":9007200869124390000,"key":"create-remote-file-node-https://res.cloudinary.com/blackswanfarming/images/f_auto,q_auto/v1613032087/W/Call-Option-Asymmetric-Payoff/Call-Option-Asymmetric-Payoff.png","val":{"content-type":"image/png","etag":"\"ccfd9006fbff5d708d50333f1d407aa2\"","last-modified":"Tue, 16 Feb 2021 01:50:18 GMT","content-length":"11217","date":"Fri, 26 Feb 2021 23:49:59 GMT","connection":"close","cache-control":"private, no-transform, immutable, max-age=2592000","access-control-expose-headers":"Content-Length,Content-Disposition,Content-Range,Etag,Server-Timing,Vary,X-Cld-Error,X-Content-Type-Options","access-control-allow-origin":"*","accept-ranges":"bytes","timing-allow-origin":"*","server":"Cloudinary","strict-transport-security":"max-age=604800","vary":"Accept,User-Agent,Save-Data","x-content-type-options":"nosniff","server-timing":"akam;dur=329;cpu=26;start=2021-02-26T23:49:58.893Z;desc=miss,rtt;dur=52,cloudinary;dur=73;start=2021-02-26T23:49:59.035Z"}}